dashboard/__init__.py
dashboard/covid_data_handler.py
dashboard/covid_news_handling.py
dashboard/main.py
dashboard/time_handler.py
covid_dashboard_jadam-0.0.1.dist-info/METADATA
covid_dashboard_jadam-0.0.1.dist-info/WHEEL
covid_dashboard_jadam-0.0.1.dist-info/top_level.txt
covid_dashboard_jadam-0.0.1.dist-info/RECORD
