Metadata-Version: 2.1
Name: covid-dashboard-jadam
Version: 0.0.1
Summary: A dashboard to display up to date covid data and news
Home-page: UNKNOWN
Author: James Adam
Author-email: ja669@exeter.ac.uk
License: UNKNOWN
Platform: UNKNOWN
Requires-Python: >=3.9
